behaverify/__init__.py
behaverify/__main__.py
behaverify/behaverify.py
behaverify/behaverify_common.py
behaverify/behaverify_gui.py
behaverify/behaverify_to_smv.py
behaverify/check_grammar.py
behaverify/counter_trace.py
behaverify/dsl_to_cpp.py
behaverify/dsl_to_haskell.py
behaverify/dsl_to_latex.py
behaverify/dsl_to_nuxmv.py
behaverify/dsl_to_python.py
behaverify/meta_functions.py
behaverify/meta_functions_neural.py
behaverify/model_to_dsl.py
behaverify/node_creator.py
behaverify/data/haskell_files/BehaviorTreeBlackboard.hs
behaverify/data/haskell_files/BehaviorTreeCore.hs
behaverify/data/haskell_files/BehaviorTreeEnvironment.hs
behaverify/data/metamodel/README.md
behaverify/data/metamodel/behaverify.tx
behaverify/data/tick_overwrite/tick_overwrite.py
behaverify/data/tikz_files/end.tex
behaverify/data/tikz_files/start.tex
behaverify/grid_world_draw/__init__.py
behaverify/grid_world_draw/default_dictionary.py
behaverify/grid_world_draw/draw_output.py
behaverify/grid_world_draw/misc_util.py
behaverify/grid_world_draw/parse_nuxmv_output.py
behaverify/grid_world_draw/parse_python_output.py
behaverify/grid_world_draw/unused/create_grid.py
behaverify/grid_world_draw/unused/draw_network.py
behaverify/grid_world_draw/unused/draw_obstacles.py
behaverify/grid_world_draw/unused/parse_nuxmv_output_stage_0.py
behaverify/grid_world_draw/unused/parse_nuxmv_output_stage_1.py
behaverify/grid_world_draw/unused/parse_nuxmv_output_stage_LAST.py
behaverify/monitor/create_c_monitor.py
behaverify/monitor/create_dsl_monitor.py
behaverify/monitor/create_python_monitor.py
behaverify/variations/__init__.py
behaverify/variations/naive/__init__.py
behaverify/variations/naive/behaverify_to_smv.py
behaverify/variations/naive/node_creator.py
behaverify/variations/unused/aut/behaverify_common.py
behaverify/variations/unused/aut/behaverify_to_smv.py
behaverify/variations/unused/aut/check_model.py
behaverify/variations/unused/aut/dsl_to_behaverify.py
behaverify-1.0.0.dist-info/licenses/LICENSE
behaverify-1.0.0.dist-info/METADATA
behaverify-1.0.0.dist-info/WHEEL
behaverify-1.0.0.dist-info/entry_points.txt
behaverify-1.0.0.dist-info/top_level.txt
behaverify-1.0.0.dist-info/RECORD
