Metadata-Version: 2.4
Name: behaverify
Version: 1.0.0
Summary: A tool for formal verification of behavior trees
Author-email: Serena Serafina Serbinowska <serena.serbinowska.work@proton.me>
License-Expression: MIT
Project-URL: Homepage, https://github.com/verivital/behaverify
Project-URL: Repository, https://github.com/verivital/behaverify
Project-URL: Documentation, https://github.com/verivital/behaverify
Project-URL: Bug Tracker, https://github.com/verivital/behaverify/issues
Keywords: behavior-trees,formal-verification,model-checking,nuXmv
Classifier: Development Status :: 5 - Production/Stable
Classifier: Intended Audience :: Developers
Classifier: Intended Audience :: Science/Research
Classifier: Operating System :: OS Independent
Classifier: Programming Language :: Python :: 3
Classifier: Programming Language :: Python :: 3.10
Classifier: Programming Language :: Python :: 3.11
Classifier: Programming Language :: Python :: 3.12
Classifier: Topic :: Scientific/Engineering
Classifier: Topic :: Scientific/Engineering :: Artificial Intelligence
Classifier: Topic :: Software Development :: Libraries :: Python Modules
Classifier: Topic :: Software Development :: Quality Assurance
Requires-Python: >=3.10
License-File: LICENSE
Requires-Dist: py-trees>=2.2.3
Requires-Dist: textX>=4.1.0
Requires-Dist: onnx>=1.18.0
Requires-Dist: onnxruntime>=1.22.1
Requires-Dist: graphviz>=0.20.3
Requires-Dist: pillow>=11.1.0
Requires-Dist: pandas>=2.2.3
Requires-Dist: Jinja2>=3.1.5
Requires-Dist: matplotlib>=3.10.0
Provides-Extra: dev
Requires-Dist: pytest>=8.0.0; extra == "dev"
Requires-Dist: pytest-cov>=4.1.0; extra == "dev"
Dynamic: license-file
